LICENSE
MANIFEST.in
README.markdown
pdc.bash
setup.py
tox.ini
bin/pdc
bin/pdc_client
docs/.gitignore
docs/LICENSE_sphinx_deployment
docs/Makefile
docs/pdc_client.1
docs/sphinx_deployment.mk
docs/source/api.rst
docs/source/conf.py
docs/source/config.rst
docs/source/index.rst
docs/source/install.rst
docs/source/pdc.rst
docs/source/pdc_client.rst
docs/source/release.rst
pdc_client/__init__.py
pdc_client/compat.py
pdc_client/plugin_helpers.py
pdc_client/runner.py
pdc_client/test_helpers.py
pdc_client.egg-info/PKG-INFO
pdc_client.egg-info/SOURCES.txt
pdc_client.egg-info/dependency_links.txt
pdc_client.egg-info/requires.txt
pdc_client.egg-info/top_level.txt
pdc_client/plugins/__init__.py
pdc_client/plugins/base_product.py
pdc_client/plugins/build_image_rtt_tests.py
pdc_client/plugins/build_images.py
pdc_client/plugins/component.py
pdc_client/plugins/compose.py
pdc_client/plugins/compose_full_import.py
pdc_client/plugins/compose_image_rtt_tests.py
pdc_client/plugins/compose_tree_locations.py
pdc_client/plugins/contact.py
pdc_client/plugins/group_resource_permissions.py
pdc_client/plugins/image.py
pdc_client/plugins/permission.py
pdc_client/plugins/product.py
pdc_client/plugins/product_version.py
pdc_client/plugins/release.py
pdc_client/plugins/release_variant.py
pdc_client/plugins/repo.py
pdc_client/plugins/rpm.py
requirements/devel.txt
requirements/production.txt
tests/__init__.py
tests/tests.py
tests/api/__init__.py
tests/api/tests.py
tests/base_product/__init__.py
tests/base_product/tests.py
tests/base_product/data/info.txt
tests/base_product/data/list-all.txt
tests/base_product/data/list-empty.txt
tests/build_image/__init__.py
tests/build_image/tests.py
tests/build_image/data/detail.json
tests/build_image/data/detail.txt
tests/build_image/data/list_multi_page.txt
tests/build_image_rtt_tests/__init__.py
tests/build_image_rtt_tests/tests.py
tests/build_image_rtt_tests/data/build_image_rtt_tests.txt
tests/build_image_rtt_tests/data/detail.json
tests/build_image_rtt_tests/data/list.txt
tests/component/__init__.py
tests/component/tests.py
tests/component/data/global_component/detail.json
tests/component/data/global_component/detail.txt
