Metadata-Version: 1.1
Name: pdc-client
Version: 1.8.0
Summary: Client library and console client for Product Definition Center
Home-page: https://github.com/product-definition-center/pdc-client
Author: UNKNOWN
Author-email: UNKNOWN
License: MIT
Download-URL: https://github.com/product-definition-center/pdc-client/releases
Platform: UNKNOWN
Classifier: Development Status :: 4 - Beta
Classifier: Intended Audience :: Developers
Classifier: License :: OSI Approved :: MIT License
Classifier: Topic :: Software Development :: Libraries
Classifier: Topic :: Utilities
